AUTHORS.md
CODE_OF_CONDUCT.md
CONTRIBUTING.md
LICENSE.md
MANIFEST.in
README.md
pyproject.toml
setup.cfg
setup.py
librosa/__init__.py
librosa/_cache.py
librosa/beat.py
librosa/decompose.py
librosa/display.py
librosa/effects.py
librosa/filters.py
librosa/onset.py
librosa/segment.py
librosa/sequence.py
librosa/version.py
librosa/core/__init__.py
librosa/core/audio.py
librosa/core/constantq.py
librosa/core/convert.py
librosa/core/fft.py
librosa/core/harmonic.py
librosa/core/notation.py
librosa/core/pitch.py
librosa/core/spectrum.py
librosa/feature/__init__.py
librosa/feature/inverse.py
librosa/feature/rhythm.py
librosa/feature/spectral.py
librosa/feature/utils.py
librosa/util/__init__.py
librosa/util/_nnls.py
librosa/util/decorators.py
librosa/util/deprecation.py
librosa/util/exceptions.py
librosa/util/files.py
librosa/util/matching.py
librosa/util/utils.py
librosa/util/example_data/index.json
librosa/util/example_data/registry.txt
vflibrosa.egg-info/PKG-INFO
vflibrosa.egg-info/SOURCES.txt
vflibrosa.egg-info/dependency_links.txt
vflibrosa.egg-info/requires.txt
vflibrosa.egg-info/top_level.txt