Metadata-Version: 2.1
Name: vflibrosa
Version: 0.8.1
Summary: Python module for audio and music processing
Home-page: https://librosa.org
Author: Brian McFee, librosa development team
Author-email: brian.mcfee@nyu.edu
License: ISC
Project-URL: Documentation, https://librosa.org/doc
Project-URL: Download, https://github.com/librosa/librosa/releases
Project-URL: Source, https://github.com/librosa/librosa
Project-URL: Tracker, https://github.com/librosa/librosa/issues
Project-URL: Discussion forum, https://groups.google.com/g/librosa
Classifier: License :: OSI Approved :: ISC License (ISCL)
Classifier: Programming Language :: Python
Classifier: Development Status :: 3 - Alpha
Classifier: Intended Audience :: Developers
Classifier: Topic :: Multimedia :: Sound/Audio :: Analysis
Classifier: Framework :: Matplotlib
Classifier: Programming Language :: Python :: 3
Classifier: Programming Language :: Python :: 3.6
Classifier: Programming Language :: Python :: 3.7
Classifier: Programming Language :: Python :: 3.8
Classifier: Programming Language :: Python :: 3.9
Requires-Python: >=3.6
Provides-Extra: docs
Provides-Extra: tests
Provides-Extra: display
License-File: LICENSE.md
